mylibrary/__init__.py
mylibrary/blessed.py
blessedlib-0.1.0.dist-info/METADATA
blessedlib-0.1.0.dist-info/WHEEL
blessedlib-0.1.0.dist-info/top_level.txt
blessedlib-0.1.0.dist-info/RECORD
