Metadata-Version: 2.1
Name: blessedlib
Version: 0.1.0
Summary: A library for cracking hashes, developed by Team Blessed
Author: blessed
Author-email: example@example.com
Classifier: Programming Language :: Python :: 3
Classifier: License :: OSI Approved :: MIT License
Classifier: Operating System :: OS Independent
Requires-Python: >=3.6
Requires-Dist: hashlib
